views_forecasts/__init__.py
views_forecasts/db_ops.py
views_forecasts/example_data.py
views_forecasts/extensions.py
views_forecasts/file_ops.py
views_forecasts-0.5.5.dist-info/METADATA
views_forecasts-0.5.5.dist-info/WHEEL
views_forecasts-0.5.5.dist-info/RECORD
