Metadata-Version: 2.1
Name: views_forecasts
Version: 0.5.5
Summary: Forecast store for ViEWS3.
Home-page: https://github.com/UppsalaConflictDataProgram/views_forecasts>
License: MIT
Author: Mihai Croicu
Author-email: mihai.croicu@pcr.uu.se
Requires-Python: >=3.8,<4.0
Classifier: License :: OSI Approved :: MIT License
Classifier: Programming Language :: Python :: 3
Classifier: Programming Language :: Python :: 3.8
Classifier: Programming Language :: Python :: 3.9
Classifier: Programming Language :: Python :: 3.10
Classifier: Programming Language :: Python :: 3.11
Classifier: Programming Language :: Python :: 3.12
Requires-Dist: cryptography (>3.4.5,<50.0.0)
Requires-Dist: numpy (>=1.20,<2.0)
Requires-Dist: pandas (>=1.2.3,<2.0.0)
Requires-Dist: psycopg2 (>=2.8.1,<3.0.0)
Requires-Dist: python-dotenv (>=0.18,<0.19)
Requires-Dist: sqlalchemy (>=1.3,<2.0)
Requires-Dist: views-runs (>=1.13.1,<2.0.0)
Requires-Dist: views-storage (>=1.1.4,<2.0.0)
Requires-Dist: viewser (>5.13.0,<7.0.0)
